avro_models/__init__.py
avro_models/core.py
avro_models/models.py
avro_models/utils.py
example/__init__.py
example/example.py
example/example_models.py
avro_models-1.0.1.dist-info/LICENSE.md
avro_models-1.0.1.dist-info/METADATA
avro_models-1.0.1.dist-info/WHEEL
avro_models-1.0.1.dist-info/top_level.txt
avro_models-1.0.1.dist-info/RECORD
