Metadata-Version: 2.1
Name: avro-models
Version: 1.0.1
Summary: Object-relational mapping for AVRO schema
Home-page: https://github.com/kun-fang/avro-data-model
Author: Kun Fang
Author-email: kfang_anqing@yahoo.com
License: UNKNOWN
Keywords: avro avro-schema orm python3 avro-data data-models
Platform: UNKNOWN
Classifier: Programming Language :: Python :: 3
Classifier: License :: OSI Approved :: MIT License
Classifier: Operating System :: OS Independent
Requires-Dist: avro-python3 (>=1.8.2)
Requires-Dist: six (>=1.11.0)
